cleverdoc/VERSION
cleverdoc/__init__.py
cleverdoc/enums.py
cleverdoc/license.py
cleverdoc/params.py
cleverdoc/__custom_pycache__/enums_080b72669d9c4d8f9898c5dd5616b150.cpython-xxx.pyc
cleverdoc/__custom_pycache__/enums_0bcd0fbbd8bc4d3ca71a6934edc3a73c.cpython-xxx.pyc
cleverdoc/__custom_pycache__/enums_0c2030afbc1d41389c1cdf580b14b2d6.cpython-xxx.pyc
cleverdoc/__custom_pycache__/enums_0e5cea58090545809976ec7f56347d20.cpython-xxx.pyc
cleverdoc/__custom_pycache__/enums_0f4a28f6d37b421db42e82c81d1d24fc.cpython-xxx.pyc
cleverdoc/__custom_pycache__/enums_18575b18f81a403cad7504e861e1121a.cpython-xxx.pyc
cleverdoc/__custom_pycache__/enums_1c3367a45dc74a0d866f5439d155e5f7.cpython-xxx.pyc
cleverdoc/__custom_pycache__/enums_27b0ee336845462e9d683e8d7553b8ad.cpython-xxx.pyc
cleverdoc/__custom_pycache__/enums_2bb2e9cada4e4481958e50bef9b3ff19.cpython-xxx.pyc
cleverdoc/__custom_pycache__/enums_3819829364d34c3586e4d91eb1cdd31f.cpython-xxx.pyc
cleverdoc/__custom_pycache__/enums_4a00623aec2e4fd6a19ad4cc69d46775.cpython-xxx.pyc
cleverdoc/__custom_pycache__/enums_64266823e1b0472b800c6f27a6ace4ed.cpython-xxx.pyc
cleverdoc/__custom_pycache__/enums_677c24e4557a4c9591e61058a08d4ffa.cpython-xxx.pyc
cleverdoc/__custom_pycache__/enums_6e4685167b9244e8bde0c50c5a35cf3a.cpython-xxx.pyc
cleverdoc/__custom_pycache__/enums_6fe4fd3caa7445648c57eaba305229c4.cpython-xxx.pyc
cleverdoc/__custom_pycache__/enums_7c6b63a868ab4694b8617237b8f4f562.cpython-xxx.pyc
cleverdoc/__custom_pycache__/enums_7ff08ee336914b4595529d0544ca11e4.cpython-xxx.pyc
cleverdoc/__custom_pycache__/enums_8198c5afe01048c185f0202e660a98a2.cpython-xxx.pyc
cleverdoc/__custom_pycache__/enums_88e9f1a9304a4da6a5cc86cf410b6940.cpython-xxx.pyc
cleverdoc/__custom_pycache__/enums_89c31a67f8134e1f9c4965d99b693513.cpython-xxx.pyc
cleverdoc/__custom_pycache__/enums_8c1317004424489daa4b361ea8717720.cpython-xxx.pyc
cleverdoc/__custom_pycache__/enums_97fe298169eb4acc8026d94319283de6.cpython-xxx.pyc
cleverdoc-1.0.6.dist-info/METADATA
cleverdoc-1.0.6.dist-info/WHEEL
cleverdoc-1.0.6.dist-info/top_level.txt
cleverdoc-1.0.6.dist-info/RECORD
