Metadata-Version: 2.1
Name: cleverdoc
Version: 1.0.6
Summary: AI lib for processing and de-identification medical documents and images.
Home-page: http://apicom.pro
Author: ApicomPro
Author-email: info@apicom.pro
Project-URL: Documentation, https://cleverdoc.apicom.pro/
Project-URL: Workshop, https://github.com/ApiComPro/cleverdoc-workshop
Classifier: Programming Language :: Python :: 3
Classifier: Operating System :: OS Independent
Requires-Python: >=3.9
Requires-Dist: pyspark <=3.4.2,>=3.0.2
Requires-Dist: pyarrow
Requires-Dist: tesserocr
Requires-Dist: numpy
Requires-Dist: pandas
Requires-Dist: pillow
Requires-Dist: PyMuPDF
Requires-Dist: pyJWT
Requires-Dist: cryptography
Provides-Extra: inference
Requires-Dist: optimum[onnxruntime] ; extra == 'inference'
Provides-Extra: llm
Requires-Dist: openai ; extra == 'llm'
